<?xml version="1.0" encoding="utf-8"?>
<!DOCTYPE hibernate-mapping PUBLIC "-//Hibernate/Hibernate Mapping DTD 3.0//EN"
"http://hibernate.sourceforge.net/hibernate-mapping-3.0.dtd">
<!-- 
    Mapping file autogenerated
-->
<hibernate-mapping>
    <class name="com.dixin.hibernate.Arrivement" table="arrivement" catalog="dixin">
        <id name="id" type="java.lang.Integer">
            <column name="id" />
            <generator class="increment" />
        </id>
        <many-to-one name="employee" class="com.dixin.hibernate.Employee" fetch="select">
            <column name="fk_employee_id" not-null="true" />
        </many-to-one>
        <property name="arriveDate" type="java.util.Date">
            <column name="arrive_date" length="19" not-null="true" />
        </property>
        <set name="arrivedetails" inverse="true">
            <key>
                <column name="fk_arrivement_id" not-null="true" />
            </key>
            <one-to-many class="com.dixin.hibernate.Arrivedetail" />
        </set>
        <property name="arriveNo" type="java.lang.String">
        	<column name="arrive_no" not-null="false" />
        </property>
        <property name="doubleCheck" type="java.lang.Integer">
            <column name="doubleCheck" not-null="true" />
        </property>
         <property name="checker" type="java.lang.String">
        	<column name="checker" not-null="false" />
        </property>
    </class>
</hibernate-mapping>
